napari_mzarr/__init__.py
napari_mzarr/_reader.py
napari_mzarr/_writer.py
napari_mzarr/napari.yaml
napari_mzarr-0.0.3.dist-info/LICENSE
napari_mzarr-0.0.3.dist-info/METADATA
napari_mzarr-0.0.3.dist-info/WHEEL
napari_mzarr-0.0.3.dist-info/entry_points.txt
napari_mzarr-0.0.3.dist-info/top_level.txt
napari_mzarr-0.0.3.dist-info/RECORD
